fastomit/__about__.c
fastomit/__about__.html
fastomit/__about__.py
fastomit/__init__.c
fastomit/__init__.html
fastomit/__init__.py
fastomit/omit.cpp
fastomit/omit.html
fastomit/omit.pyi
fastomit/omit.pyx
fastomit/types.c
fastomit/types.html
fastomit/types.py
fastomit/__about__.cp38-win_amd64.pyd
fastomit/__init__.cp38-win_amd64.pyd
fastomit/omit.cp38-win_amd64.pyd
fastomit/types.cp38-win_amd64.pyd
fastomit-0.1.1.dist-info/METADATA
fastomit-0.1.1.dist-info/WHEEL
fastomit-0.1.1.dist-info/licenses/LICENSE.txt
fastomit-0.1.1.dist-info/RECORD
